[
	{
		"id": "1",
		"first_name": "Jeanette",
		"last_name": "Penddreth",
		"email": "jpenddreth0@census.gov",
		"gender": "Female",
		"ip_address": "26.58.193.2"
	}, {
		"id": "2",
		"first_name": "Giavani",
		"last_name": "Frediani",
		"email": "gfrediani1@senate.gov",
		"gender": "Male",
		"ip_address": null
	}, {
		"userId": "1",
		"id": "3",
		"title": "delectus aut autem",
		"completed": true
	},
	{
		"userId": "1",
		"id": "4",
		"title": "quis ut nam facilis et officia qui",
		"completed": false
	}
]